<?xml version="1.0" encoding="UTF-8" standalone="no"?><game season="2019" tournament="FIBA"><team name="Polonia"><players><player min="11:02" name="Aleksander Roman Balcerowski" pos="2"/><player min="13:11" name="Michal Sokolowski" pos="3"/><player min="19:37" name="Aaron Cel" pos="5"/><player min="31:04" name="A.J. Slaughter" pos="6"/><player min="29:10" name="Mateusz Ponitka" pos="9"/><player min="36:40" name="Adam Waczynski" pos="12"/><player min="No Jugó - Decisión de entrenador" name="Dominik Olejniczak" pos="13"/><player min="No Jugó - Decisión de entrenador" name="Kamil Laczynski" pos="15"/><player min="02:03" name="Karol Gruszecki" pos="33"/><player min="26:56" name="Adam Hrycaniuk" pos="34"/><player min="14:54" name="Lukasz Koszarek" pos="55"/><player min="15:23" name="Damian Kulig" pos="77"/></players></team><team name="Rusia"><players><player min="No Jugó - Decisión de entrenador" name="Andrei Sopin" pos="2"/><player min="17:34" name="Sergey Karasev" pos="3"/><player min="05:09" name="Evgenii Baburin" pos="4"/><player min="11:40" name="Grigory Motovilov" pos="6"/><player min="24:59" name="Vitaly Fridzon" pos="7"/><player min="12:49" name="Vladimir Ivlev" pos="8"/><player min="18:42" name="Semen Antonov" pos="11"/><player min="19:41" name="Andrey Zubkov" pos="12"/><player min="29:54" name="Andrey Vorontsevich" pos="20"/><player min="28:46" name="Mikhail Kulagin" pos="30"/><player min="No Jugó - Decisión de entrenador" name="Evgeny Valiev" pos="31"/><player min="30:46" name="Nikita Kurbanov" pos="41"/></players></team></game>